Metadata-Version: 2.1
Name: magic-calculator
Version: 0.5
Summary: performs magic calculation
Home-page: https://github.com/soumen448/magic_calculator
Author: Soumen Mondal
Author-email: mondalsoumen00@gmail.com
License: MIT
Download-URL: https://github.com/soumen448/magic_calculator/archive/refs/tags/0.5.tar.gz
Keywords: pypi,magic_calculator,tutorial
Platform: UNKNOWN
Classifier: Development Status :: 3 - Alpha
Classifier: Intended Audience :: Developers
Classifier: License :: OSI Approved :: MIT License
Classifier: Programming Language :: Python :: 3.9
License-File: LICENSE.txt
